pyramid_csp/__init__.py
pyramid_csp-0.1.0.dist-info/LICENSE
pyramid_csp-0.1.0.dist-info/METADATA
pyramid_csp-0.1.0.dist-info/WHEEL
pyramid_csp-0.1.0.dist-info/top_level.txt
pyramid_csp-0.1.0.dist-info/RECORD
