Metadata-Version: 2.1
Name: pyramid-csp
Version: 0.1.0
Summary: Content Security Policy add-on for Pyramid.
Home-page: https://github.com/luhn/pyramid-csp
Author: Theron Luhn
Author-email: theron@luhn.com
Classifier: Development Status :: 4 - Beta
Classifier: Framework :: Pyramid
Classifier: Intended Audience :: Developers
Classifier: License :: OSI Approved :: MIT License
Classifier: Operating System :: OS Independent
Classifier: Programming Language :: Python :: 3 :: Only
Classifier: Programming Language :: Python :: 3
Classifier: Programming Language :: Python :: 3.8
Classifier: Programming Language :: Python :: 3.9
Classifier: Programming Language :: Python :: 3.10
Classifier: Programming Language :: Python :: 3.11
Classifier: Programming Language :: Python :: 3.12
Classifier: Programming Language :: Python :: Implementation :: CPython
Classifier: Programming Language :: Python :: Implementation :: PyPy
Classifier: Programming Language :: Python
Requires-Python: >=3.8
License-File: LICENSE
Requires-Dist: pyramid >=2
Provides-Extra: linting
Requires-Dist: ruff ~=0.1.6 ; extra == 'linting'
Requires-Dist: black ~=23.11 ; extra == 'linting'
Requires-Dist: isort ~=5.12 ; extra == 'linting'
Provides-Extra: testing
Requires-Dist: pytest ~=7.4 ; extra == 'testing'
Requires-Dist: webtest ~=3.0 ; extra == 'testing'
